{
    "stations": {
        "Alewife": {
            "label": "Alewife",
            "lon": -71.141287,
            "lat": 42.39583
        },
        "Allston Street": {
            "label": "Allston Street",
            "lon": -71.137955,
            "lat": 42.348701
        },
        "Amory Street": {
            "label": "Amory Street",
            "lon": -71.114748,
            "lat": 42.350992
        },
        "Andrew": {
            "label": "Andrew",
            "lon": -71.057655,
            "lat": 42.330154
        },
        "Airport": {
            "label": "Airport",
            "lon": -71.030395,
            "lat": 42.374262
        },
        "Aquarium": {
            "label": "Aquarium",
            "lon": -71.051652,
            "lat": 42.359784
        },
        "Arlington": {
            "label": "Arlington",
            "lon": -71.070893,
            "lat": 42.351902
        },
        "Ashmont": {
            "label": "Ashmont",
            "lon": -71.063777,
            "lat": 42.28452
        },
        "Assembly": {
            "label": "Assembly",
            "lon": -71.077257,
            "lat": 42.392811
        },
        "Babcock Street": {
            "label": "Babcock Street",
            "lon": -71.119924,
            "lat": 42.351616
        },
        "Ball Square": {
            "label": "Ball Square",
            "lon": -71.111003,
            "lat": 42.399889
        },
        "Back Bay": {
            "label": "Back Bay",
            "lon": -71.075727,
            "lat": 42.34735
        },
        "Back of the Hill": {
            "label": "Back of the Hill",
            "lon": -71.111313,
            "lat": 42.330139
        },
        "Beaconsfield": {
            "label": "Beaconsfield",
            "lon": -71.140455,
            "lat": 42.335765
        },
        "Washington Square": {
            "label": "Washington Square",
            "lon": -71.13533,
            "lat": 42.339394
        },
        "Blandford Street": {
            "label": "Blandford Street",
            "lon": -71.100258,
            "lat": 42.349293
        },
        "Beachmont": {
            "label": "Beachmont",
            "lon": -70.992319,
            "lat": 42.397542
        },
        "Brandon Hall": {
            "label": "Brandon Hall",
            "lon": -71.129082,
            "lat": 42.340023
        },
        "Bowdoin": {
            "label": "Bowdoin",
            "lon": -71.062037,
            "lat": 42.361365
        },
        "Boylston": {
            "label": "Boylston",
            "lon": -71.06459,
            "lat": 42.35302
        },
        "Broadway": {
            "label": "Broadway",
            "lon": -71.056967,
            "lat": 42.342622
        },
        "Packard's Corner": {
            "label": "Packard's Corner",
            "lon": -71.125031,
            "lat": 42.351967
        },
        "Brookline Hills": {
            "label": "Brookline Hills",
            "lon": -71.126683,
            "lat": 42.331316
        },
        "Brigham Circle": {
            "label": "Brigham Circle",
            "lon": -71.104609,
            "lat": 42.334229
        },
        "Braintree": {
            "label": "Braintree",
            "lon": -71.001138,
            "lat": 42.207854
        },
        "Boston University Central": {
            "label": "Boston University Central",
            "lon": -71.106865,
            "lat": 42.350082
        },
        "Boston University East": {
            "label": "Boston University East",
            "lon": -71.103889,
            "lat": 42.349735
        },
        "Butler": {
            "label": "Butler",
            "lon": -71.062519,
            "lat": 42.272429
        },
        "Brookline Village": {
            "label": "Brookline Village",
            "lon": -71.116857,
            "lat": 42.332608
        },
        "Capen Street": {
            "label": "Capen Street",
            "lon": -71.087338,
            "lat": 42.267563
        },
        "Community College": {
            "label": "Community College",
            "lon": -71.069533,
            "lat": 42.373622
        },
        "Cedar Grove": {
            "label": "Cedar Grove",
            "lon": -71.060394,
            "lat": 42.279629
        },
        "Central Avenue": {
            "label": "Central Avenue",
            "lon": -71.073444,
            "lat": 42.270027
        },
        "Chestnut Hill": {
            "label": "Chestnut Hill",
            "lon": -71.164699,
            "lat": 42.326753
        },
        "Chestnut Hill Avenue": {
            "label": "Chestnut Hill Avenue",
            "lon": -71.15316,
            "lat": 42.338169
        },
        "Charles/MGH": {
            "label": "Charles/MGH",
            "lon": -71.070628,
            "lat": 42.361166
        },
        "Chinatown": {
            "label": "Chinatown",
            "lon": -71.062752,
            "lat": 42.352547
        },
        "Chiswick Road": {
            "label": "Chiswick Road",
            "lon": -71.150711,
            "lat": 42.340805
        },
        "Cleveland Circle": {
            "label": "Cleveland Circle",
            "lon": -71.149326,
            "lat": 42.336142
        },
        "Central": {
            "label": "Central",
            "lon": -71.103802,
            "lat": 42.365486
        },
        "Copley": {
            "label": "Copley",
            "lon": -71.077447,
            "lat": 42.349974
        },
        "Silver Line Way": {
            "label": "Silver Line Way",
            "lon": -71.038385,
            "lat": 42.347154
        },
        "Coolidge Corner": {
            "label": "Coolidge Corner",
            "lon": -71.121263,
            "lat": 42.342116
        },
        "Davis": {
            "label": "Davis",
            "lon": -71.121815,
            "lat": 42.39674
        },
        "Dean Road": {
            "label": "Dean Road",
            "lon": -71.141853,
            "lat": 42.337807
        },
        "Downtown Crossing": {
            "label": "Downtown Crossing",
            "lon": -71.060225,
            "lat": 42.355518
        },
        "Eliot": {
            "label": "Eliot",
            "lon": -71.216684,
            "lat": 42.319045
        },
        "Englewood Avenue": {
            "label": "Englewood Avenue",
            "lon": -71.14566,
            "lat": 42.336971
        },
        "East Somerville": {
            "label": "East Somerville",
            "lon": -71.086625,
            "lat": 42.379467
        },
        "Fairbanks Street": {
            "label": "Fairbanks Street",
            "lon": -71.131073,
            "lat": 42.339725
        },
        "Fenwood Road": {
            "label": "Fenwood Road",
            "lon": -71.105728,
            "lat": 42.333706
        },
        "Fenway": {
            "label": "Fenway",
            "lon": -71.104213,
            "lat": 42.345403
        },
        "Fields Corner": {
            "label": "Fields Corner",
            "lon": -71.061667,
            "lat": 42.300093
        },
        "Forest Hills": {
            "label": "Forest Hills",
            "lon": -71.113943,
            "lat": 42.300713
        },
        "Gilman Square": {
            "label": "Gilman Square",
            "lon": -71.096766,
            "lat": 42.387928
        },
        "Government Center": {
            "label": "Government Center",
            "lon": -71.059215,
            "lat": 42.359705
        },
        "Griggs Street": {
            "label": "Griggs Street",
            "lon": -71.134949,
            "lat": 42.348545
        },
        "Green Street": {
            "label": "Green Street",
            "lon": -71.107414,
            "lat": 42.310525
        },
        "Haymarket": {
            "label": "Haymarket",
            "lon": -71.05829,
            "lat": 42.363021
        },
        "Harvard": {
            "label": "Harvard",
            "lon": -71.118956,
            "lat": 42.373362
        },
        "Harvard Avenue": {
            "label": "Harvard Avenue",
            "lon": -71.131355,
            "lat": 42.350243
        },
        "Heath Street": {
            "label": "Heath Street",
            "lon": -71.110252,
            "lat": 42.328316
        },
        "Hawes Street": {
            "label": "Hawes Street",
            "lon": -71.111145,
            "lat": 42.344906
        },
        "Hynes Convention Center": {
            "label": "Hynes Convention Center",
            "lon": -71.087903,
            "lat": 42.347888
        },
        "Jackson Square": {
            "label": "Jackson Square",
            "lon": -71.099592,
            "lat": 42.323132
        },
        "JFK/UMass": {
            "label": "JFK/UMass",
            "lon": -71.052391,
            "lat": 42.320685
        },
        "Kenmore": {
            "label": "Kenmore",
            "lon": -71.095169,
            "lat": 42.348949
        },
        "Kendall/MIT": {
            "label": "Kendall/MIT",
            "lon": -71.086176,
            "lat": 42.362491
        },
        "Kent Street": {
            "label": "Kent Street",
            "lon": -71.114197,
            "lat": 42.344074
        },
        "Boston College": {
            "label": "Boston College",
            "lon": -71.166769,
            "lat": 42.340081
        },
        "Lechmere": {
            "label": "Lechmere",
            "lon": -71.076584,
            "lat": 42.371572
        },
        "Longwood Medical Area": {
            "label": "Longwood Medical Area",
            "lon": -71.100052,
            "lat": 42.33596
        },
        "Longwood": {
            "label": "Longwood",
            "lon": -71.109956,
            "lat": 42.341702
        },
        "Massachusetts Avenue": {
            "label": "Massachusetts Avenue",
            "lon": -71.083423,
            "lat": 42.341512
        },
        "Mattapan": {
            "label": "Mattapan",
            "lon": -71.092486,
            "lat": 42.26762
        },
        "Medford/Tufts": {
            "label": "Medford/Tufts",
            "lon": -71.117044,
            "lat": 42.407975
        },
        "Museum of Fine Arts": {
            "label": "Museum of Fine Arts",
            "lon": -71.095512,
            "lat": 42.337711
        },
        "Magoun Square": {
            "label": "Magoun Square",
            "lon": -71.106388,
            "lat": 42.393682
        },
        "Milton": {
            "label": "Milton",
            "lon": -71.067266,
            "lat": 42.270349
        },
        "Mission Park": {
            "label": "Mission Park",
            "lon": -71.109756,
            "lat": 42.333195
        },
        "Malden Center": {
            "label": "Malden Center",
            "lon": -71.07411,
            "lat": 42.426632
        },
        "Maverick": {
            "label": "Maverick",
            "lon": -71.03953,
            "lat": 42.369119
        },
        "Newton Highlands": {
            "label": "Newton Highlands",
            "lon": -71.205509,
            "lat": 42.322381
        },
        "Newton Centre": {
            "label": "Newton Centre",
            "lon": -71.192414,
            "lat": 42.329443
        },
        "North Station": {
            "label": "North Station",
            "lon": -71.06129,
            "lat": 42.365577
        },
        "North Quincy": {
            "label": "North Quincy",
            "lon": -71.029583,
            "lat": 42.275275
        },
        "Nubian": {
            "label": "Nubian",
            "lon": -71.083982,
            "lat": 42.329544
        },
        "Northeastern University": {
            "label": "Northeastern University",
            "lon": -71.088806,
            "lat": 42.340401
        },
        "Oak Grove": {
            "label": "Oak Grove",
            "lon": -71.071097,
            "lat": 42.43668
        },
        "Orient Heights": {
            "label": "Orient Heights",
            "lon": -71.004736,
            "lat": 42.386867
        },
        "Park Street": {
            "label": "Park Street",
            "lon": -71.062424,
            "lat": 42.356395
        },
        "Porter": {
            "label": "Porter",
            "lon": -71.119149,
            "lat": 42.3884
        },
        "Prudential": {
            "label": "Prudential",
            "lon": -71.081696,
            "lat": 42.34557
        },
        "Quincy Adams": {
            "label": "Quincy Adams",
            "lon": -71.007153,
            "lat": 42.233391
        },
        "Quincy Center": {
            "label": "Quincy Center",
            "lon": -71.005409,
            "lat": 42.251809
        },
        "Revere Beach": {
            "label": "Revere Beach",
            "lon": -70.992533,
            "lat": 42.407843
        },
        "Roxbury Crossing": {
            "label": "Roxbury Crossing",
            "lon": -71.095451,
            "lat": 42.331397
        },
        "Riverside": {
            "label": "Riverside",
            "lon": -71.252685,
            "lat": 42.337352
        },
        "Reservoir": {
            "label": "Reservoir",
            "lon": -71.148758,
            "lat": 42.335088
        },
        "Ruggles": {
            "label": "Ruggles",
            "lon": -71.088961,
            "lat": 42.336377
        },
        "Riverway": {
            "label": "Riverway",
            "lon": -71.111931,
            "lat": 42.331684
        },
        "Stony Brook": {
            "label": "Stony Brook",
            "lon": -71.104248,
            "lat": 42.317062
        },
        "Suffolk Downs": {
            "label": "Suffolk Downs",
            "lon": -70.997123,
            "lat": 42.390501
        },
        "Savin Hill": {
            "label": "Savin Hill",
            "lon": -71.053331,
            "lat": 42.31129
        },
        "Saint Mary's Street": {
            "label": "Saint Mary's Street",
            "lon": -71.107353,
            "lat": 42.345974
        },
        "Shawmut": {
            "label": "Shawmut",
            "lon": -71.065738,
            "lat": 42.293126
        },
        "South Street": {
            "label": "South Street",
            "lon": -71.157661,
            "lat": 42.3396
        },
        "Science Park/West End": {
            "label": "Science Park/West End",
            "lon": -71.067666,
            "lat": 42.366664
        },
        "South Station": {
            "label": "South Station",
            "lon": -71.055242,
            "lat": 42.352271
        },
        "State": {
            "label": "State",
            "lon": -71.057598,
            "lat": 42.358978
        },
        "Sutherland Road": {
            "label": "Sutherland Road",
            "lon": -71.146202,
            "lat": 42.341614
        },
        "Saint Paul Street": {
            "label": "Saint Paul Street",
            "lon": -71.116997,
            "lat": 42.343327
        },
        "Sullivan Square": {
            "label": "Sullivan Square",
            "lon": -71.076994,
            "lat": 42.383975
        },
        "Summit Avenue": {
            "label": "Summit Avenue",
            "lon": -71.12561,
            "lat": 42.34111
        },
        "Symphony": {
            "label": "Symphony",
            "lon": -71.085056,
            "lat": 42.342687
        },
        "Tappan Street": {
            "label": "Tappan Street",
            "lon": -71.138702,
            "lat": 42.338459
        },
        "Tufts Medical Center": {
            "label": "Tufts Medical Center",
            "lon": -71.063917,
            "lat": 42.349662
        },
        "Union Square": {
            "label": "Union Square",
            "lon": -71.094761,
            "lat": 42.377359
        },
        "Valley Road": {
            "label": "Valley Road",
            "lon": -71.081343,
            "lat": 42.268347
        },
        "Waban": {
            "label": "Waban",
            "lon": -71.230609,
            "lat": 42.325845
        },
        "Washington Street": {
            "label": "Washington Street",
            "lon": -71.142853,
            "lat": 42.343864
        },
        "Wellington": {
            "label": "Wellington",
            "lon": -71.077082,
            "lat": 42.40237
        },
        "Wood Island": {
            "label": "Wood Island",
            "lon": -71.022865,
            "lat": 42.37964
        },
        "Wollaston": {
            "label": "Wollaston",
            "lon": -71.020337,
            "lat": 42.266514
        },
        "Wonderland": {
            "label": "Wonderland",
            "lon": -70.991648,
            "lat": 42.41342
        },
        "Woodland": {
            "label": "Woodland",
            "lon": -71.243362,
            "lat": 42.332902
        },
        "Warren Street": {
            "label": "Warren Street",
            "lon": -71.140457,
            "lat": 42.348343
        }
    },
    "lines": [
        {
            "name": "Green Line C",
            "color": "#00843D",
            "shiftCoords": [
                0,
                0
            ],
            "nodes": [
                {
                    "coords": [
                        -71.070893,
                        42.351902
                    ],
                    "name": "Arlington",
                    "labelPos": "N"
                },
                {
                    "coords": [
                        -71.06459,
                        42.35302
                    ],
                    "name": "Boylston",
                    "labelPos": "N"
                },
                {
                    "coords": [
                        -71.077447,
                        42.349974
                    ],
                    "name": "Copley",
                    "labelPos": "N"
                },
                {
                    "coords": [
                        -71.059215,
                        42.359705
                    ],
                    "name": "Government Center",
                    "labelPos": "N"
                },
                {
                    "coords": [
                        -71.05829,
                        42.363021
                    ],
                    "name": "Haymarket",
                    "labelPos": "N"
                },
                {
                    "coords": [
                        -71.087903,
                        42.347888
                    ],
                    "name": "Hynes Convention Center",
                    "labelPos": "N"
                },
                {
                    "coords": [
                        -71.095169,
                        42.348949
                    ],
                    "name": "Kenmore",
                    "labelPos": "N"
                },
                {
                    "coords": [
                        -71.06129,
                        42.365577
                    ],
                    "name": "North Station",
                    "labelPos": "N"
                },
                {
                    "coords": [
                        -71.062424,
                        42.356395
                    ],
                    "name": "Park Street",
                    "labelPos": "N"
                },
                {
                    "coords": [
                        -71.081696,
                        42.34557
                    ],
                    "name": "Prudential",
                    "labelPos": "N"
                },
                {
                    "coords": [
                        -71.252685,
                        42.337352
                    ],
                    "name": "Riverside",
                    "labelPos": "N"
                },
                {
                    "coords": [
                        -71.085056,
                        42.342687
                    ],
                    "name": "Symphony",
                    "labelPos": "N"
                },
                {
                    "coords": [
                        -71.111003,
                        42.399889
                    ],
                    "name": "Ball Square",
                    "labelPos": "N"
                },
                {
                    "coords": [
                        -71.076584,
                        42.371572
                    ],
                    "name": "Lechmere",
                    "labelPos": "N"
                },
                {
                    "coords": [
                        -71.096766,
                        42.387928
                    ],
                    "name": "Gilman Square",
                    "labelPos": "N"
                },
                {
                    "coords": [
                        -71.117044,
                        42.407975
                    ],
                    "name": "Medford/Tufts",
                    "labelPos": "N"
                },
                {
                    "coords": [
                        -71.094761,
                        42.377359
                    ],
                    "name": "Union Square",
                    "labelPos": "N"
                },
                {
                    "coords": [
                        -71.086625,
                        42.379467
                    ],
                    "name": "East Somerville",
                    "labelPos": "N"
                },
                {
                    "coords": [
                        -71.106388,
                        42.393682
                    ],
                    "name": "Magoun Square",
                    "labelPos": "N"
                }
            ]
        },
        {
            "name": "Green Line D",
            "color": "#00843D",
            "shiftCoords": [
                0,
                0
            ],
            "nodes": [
                {
                    "coords": [
                        -71.070893,
                        42.351902
                    ],
                    "name": "Arlington",
                    "labelPos": "N"
                },
                {
                    "coords": [
                        -71.06459,
                        42.35302
                    ],
                    "name": "Boylston",
                    "labelPos": "N"
                },
                {
                    "coords": [
                        -71.077447,
                        42.349974
                    ],
                    "name": "Copley",
                    "labelPos": "N"
                },
                {
                    "coords": [
                        -71.059215,
                        42.359705
                    ],
                    "name": "Government Center",
                    "labelPos": "N"
                },
                {
                    "coords": [
                        -71.05829,
                        42.363021
                    ],
                    "name": "Haymarket",
                    "labelPos": "N"
                },
                {
                    "coords": [
                        -71.087903,
                        42.347888
                    ],
                    "name": "Hynes Convention Center",
                    "labelPos": "N"
                },
                {
                    "coords": [
                        -71.095169,
                        42.348949
                    ],
                    "name": "Kenmore",
                    "labelPos": "N"
                },
                {
                    "coords": [
                        -71.06129,
                        42.365577
                    ],
                    "name": "North Station",
                    "labelPos": "N"
                },
                {
                    "coords": [
                        -71.062424,
                        42.356395
                    ],
                    "name": "Park Street",
                    "labelPos": "N"
                },
                {
                    "coords": [
                        -71.081696,
                        42.34557
                    ],
                    "name": "Prudential",
                    "labelPos": "N"
                },
                {
                    "coords": [
                        -71.252685,
                        42.337352
                    ],
                    "name": "Riverside",
                    "labelPos": "N"
                },
                {
                    "coords": [
                        -71.085056,
                        42.342687
                    ],
                    "name": "Symphony",
                    "labelPos": "N"
                },
                {
                    "coords": [
                        -71.111003,
                        42.399889
                    ],
                    "name": "Ball Square",
                    "labelPos": "N"
                },
                {
                    "coords": [
                        -71.076584,
                        42.371572
                    ],
                    "name": "Lechmere",
                    "labelPos": "N"
                },
                {
                    "coords": [
                        -71.096766,
                        42.387928
                    ],
                    "name": "Gilman Square",
                    "labelPos": "N"
                },
                {
                    "coords": [
                        -71.117044,
                        42.407975
                    ],
                    "name": "Medford/Tufts",
                    "labelPos": "N"
                },
                {
                    "coords": [
                        -71.094761,
                        42.377359
                    ],
                    "name": "Union Square",
                    "labelPos": "N"
                },
                {
                    "coords": [
                        -71.086625,
                        42.379467
                    ],
                    "name": "East Somerville",
                    "labelPos": "N"
                },
                {
                    "coords": [
                        -71.106388,
                        42.393682
                    ],
                    "name": "Magoun Square",
                    "labelPos": "N"
                }
            ]
        },
        {
            "name": "Green Line B",
            "color": "#00843D",
            "shiftCoords": [
                0,
                0
            ],
            "nodes": [
                {
                    "coords": [
                        -71.070893,
                        42.351902
                    ],
                    "name": "Arlington",
                    "labelPos": "N"
                },
                {
                    "coords": [
                        -71.06459,
                        42.35302
                    ],
                    "name": "Boylston",
                    "labelPos": "N"
                },
                {
                    "coords": [
                        -71.077447,
                        42.349974
                    ],
                    "name": "Copley",
                    "labelPos": "N"
                },
                {
                    "coords": [
                        -71.059215,
                        42.359705
                    ],
                    "name": "Government Center",
                    "labelPos": "N"
                },
                {
                    "coords": [
                        -71.05829,
                        42.363021
                    ],
                    "name": "Haymarket",
                    "labelPos": "N"
                },
                {
                    "coords": [
                        -71.087903,
                        42.347888
                    ],
                    "name": "Hynes Convention Center",
                    "labelPos": "N"
                },
                {
                    "coords": [
                        -71.095169,
                        42.348949
                    ],
                    "name": "Kenmore",
                    "labelPos": "N"
                },
                {
                    "coords": [
                        -71.06129,
                        42.365577
                    ],
                    "name": "North Station",
                    "labelPos": "N"
                },
                {
                    "coords": [
                        -71.062424,
                        42.356395
                    ],
                    "name": "Park Street",
                    "labelPos": "N"
                },
                {
                    "coords": [
                        -71.081696,
                        42.34557
                    ],
                    "name": "Prudential",
                    "labelPos": "N"
                },
                {
                    "coords": [
                        -71.252685,
                        42.337352
                    ],
                    "name": "Riverside",
                    "labelPos": "N"
                },
                {
                    "coords": [
                        -71.085056,
                        42.342687
                    ],
                    "name": "Symphony",
                    "labelPos": "N"
                },
                {
                    "coords": [
                        -71.111003,
                        42.399889
                    ],
                    "name": "Ball Square",
                    "labelPos": "N"
                },
                {
                    "coords": [
                        -71.076584,
                        42.371572
                    ],
                    "name": "Lechmere",
                    "labelPos": "N"
                },
                {
                    "coords": [
                        -71.096766,
                        42.387928
                    ],
                    "name": "Gilman Square",
                    "labelPos": "N"
                },
                {
                    "coords": [
                        -71.117044,
                        42.407975
                    ],
                    "name": "Medford/Tufts",
                    "labelPos": "N"
                },
                {
                    "coords": [
                        -71.094761,
                        42.377359
                    ],
                    "name": "Union Square",
                    "labelPos": "N"
                },
                {
                    "coords": [
                        -71.086625,
                        42.379467
                    ],
                    "name": "East Somerville",
                    "labelPos": "N"
                },
                {
                    "coords": [
                        -71.106388,
                        42.393682
                    ],
                    "name": "Magoun Square",
                    "labelPos": "N"
                }
            ]
        },
        {
            "name": "Green Line E",
            "color": "#00843D",
            "shiftCoords": [
                0,
                0
            ],
            "nodes": [
                {
                    "coords": [
                        -71.070893,
                        42.351902
                    ],
                    "name": "Arlington",
                    "labelPos": "N"
                },
                {
                    "coords": [
                        -71.06459,
                        42.35302
                    ],
                    "name": "Boylston",
                    "labelPos": "N"
                },
                {
                    "coords": [
                        -71.077447,
                        42.349974
                    ],
                    "name": "Copley",
                    "labelPos": "N"
                },
                {
                    "coords": [
                        -71.059215,
                        42.359705
                    ],
                    "name": "Government Center",
                    "labelPos": "N"
                },
                {
                    "coords": [
                        -71.05829,
                        42.363021
                    ],
                    "name": "Haymarket",
                    "labelPos": "N"
                },
                {
                    "coords": [
                        -71.087903,
                        42.347888
                    ],
                    "name": "Hynes Convention Center",
                    "labelPos": "N"
                },
                {
                    "coords": [
                        -71.095169,
                        42.348949
                    ],
                    "name": "Kenmore",
                    "labelPos": "N"
                },
                {
                    "coords": [
                        -71.06129,
                        42.365577
                    ],
                    "name": "North Station",
                    "labelPos": "N"
                },
                {
                    "coords": [
                        -71.062424,
                        42.356395
                    ],
                    "name": "Park Street",
                    "labelPos": "N"
                },
                {
                    "coords": [
                        -71.081696,
                        42.34557
                    ],
                    "name": "Prudential",
                    "labelPos": "N"
                },
                {
                    "coords": [
                        -71.252685,
                        42.337352
                    ],
                    "name": "Riverside",
                    "labelPos": "N"
                },
                {
                    "coords": [
                        -71.085056,
                        42.342687
                    ],
                    "name": "Symphony",
                    "labelPos": "N"
                },
                {
                    "coords": [
                        -71.111003,
                        42.399889
                    ],
                    "name": "Ball Square",
                    "labelPos": "N"
                },
                {
                    "coords": [
                        -71.076584,
                        42.371572
                    ],
                    "name": "Lechmere",
                    "labelPos": "N"
                },
                {
                    "coords": [
                        -71.096766,
                        42.387928
                    ],
                    "name": "Gilman Square",
                    "labelPos": "N"
                },
                {
                    "coords": [
                        -71.117044,
                        42.407975
                    ],
                    "name": "Medford/Tufts",
                    "labelPos": "N"
                },
                {
                    "coords": [
                        -71.094761,
                        42.377359
                    ],
                    "name": "Union Square",
                    "labelPos": "N"
                },
                {
                    "coords": [
                        -71.086625,
                        42.379467
                    ],
                    "name": "East Somerville",
                    "labelPos": "N"
                },
                {
                    "coords": [
                        -71.106388,
                        42.393682
                    ],
                    "name": "Magoun Square",
                    "labelPos": "N"
                }
            ]
        },
        {
            "name": "Mattapan Trolley",
            "color": "#DA291C",
            "shiftCoords": [
                0,
                0
            ],
            "nodes": []
        },
        {
            "name": "Orange Line",
            "color": "#ED8B00",
            "shiftCoords": [
                0,
                0
            ],
            "nodes": [
                {
                    "coords": [
                        -71.075727,
                        42.34735
                    ],
                    "name": "Back Bay",
                    "labelPos": "N"
                },
                {
                    "coords": [
                        -71.062752,
                        42.352547
                    ],
                    "name": "Chinatown",
                    "labelPos": "N"
                },
                {
                    "coords": [
                        -71.060225,
                        42.355518
                    ],
                    "name": "Downtown Crossing",
                    "labelPos": "N"
                },
                {
                    "coords": [
                        -71.113943,
                        42.300713
                    ],
                    "name": "Forest Hills",
                    "labelPos": "N"
                },
                {
                    "coords": [
                        -71.107414,
                        42.310525
                    ],
                    "name": "Green Street",
                    "labelPos": "N"
                },
                {
                    "coords": [
                        -71.05829,
                        42.363021
                    ],
                    "name": "Haymarket",
                    "labelPos": "N"
                },
                {
                    "coords": [
                        -71.099592,
                        42.323132
                    ],
                    "name": "Jackson Square",
                    "labelPos": "N"
                },
                {
                    "coords": [
                        -71.083423,
                        42.341512
                    ],
                    "name": "Massachusetts Avenue",
                    "labelPos": "N"
                },
                {
                    "coords": [
                        -71.06129,
                        42.365577
                    ],
                    "name": "North Station",
                    "labelPos": "N"
                },
                {
                    "coords": [
                        -71.071097,
                        42.43668
                    ],
                    "name": "Oak Grove",
                    "labelPos": "N"
                },
                {
                    "coords": [
                        -71.095451,
                        42.331397
                    ],
                    "name": "Roxbury Crossing",
                    "labelPos": "N"
                },
                {
                    "coords": [
                        -71.088961,
                        42.336377
                    ],
                    "name": "Ruggles",
                    "labelPos": "N"
                },
                {
                    "coords": [
                        -71.104248,
                        42.317062
                    ],
                    "name": "Stony Brook",
                    "labelPos": "N"
                },
                {
                    "coords": [
                        -71.063917,
                        42.349662
                    ],
                    "name": "Tufts Medical Center",
                    "labelPos": "N"
                },
                {
                    "coords": [
                        -71.076994,
                        42.383975
                    ],
                    "name": "Sullivan Square",
                    "labelPos": "N"
                },
                {
                    "coords": [
                        -71.069533,
                        42.373622
                    ],
                    "name": "Community College",
                    "labelPos": "N"
                },
                {
                    "coords": [
                        -71.077257,
                        42.392811
                    ],
                    "name": "Assembly",
                    "labelPos": "N"
                },
                {
                    "coords": [
                        -71.077082,
                        42.40237
                    ],
                    "name": "Wellington",
                    "labelPos": "N"
                },
                {
                    "coords": [
                        -71.07411,
                        42.426632
                    ],
                    "name": "Malden Center",
                    "labelPos": "N"
                }
            ]
        },
        {
            "name": "Red Line",
            "color": "#DA291C",
            "shiftCoords": [
                0,
                0
            ],
            "nodes": [
                {
                    "coords": [
                        -71.141287,
                        42.39583
                    ],
                    "name": "Alewife",
                    "labelPos": "N"
                },
                {
                    "coords": [
                        -71.057655,
                        42.330154
                    ],
                    "name": "Andrew",
                    "labelPos": "N"
                },
                {
                    "coords": [
                        -71.063777,
                        42.28452
                    ],
                    "name": "Ashmont",
                    "labelPos": "N"
                },
                {
                    "coords": [
                        -71.056967,
                        42.342622
                    ],
                    "name": "Broadway",
                    "labelPos": "N"
                },
                {
                    "coords": [
                        -71.001138,
                        42.207854
                    ],
                    "name": "Braintree",
                    "labelPos": "N"
                },
                {
                    "coords": [
                        -71.070628,
                        42.361166
                    ],
                    "name": "Charles/MGH",
                    "labelPos": "N"
                },
                {
                    "coords": [
                        -71.103802,
                        42.365486
                    ],
                    "name": "Central",
                    "labelPos": "N"
                },
                {
                    "coords": [
                        -71.121815,
                        42.39674
                    ],
                    "name": "Davis",
                    "labelPos": "N"
                },
                {
                    "coords": [
                        -71.060225,
                        42.355518
                    ],
                    "name": "Downtown Crossing",
                    "labelPos": "N"
                },
                {
                    "coords": [
                        -71.061667,
                        42.300093
                    ],
                    "name": "Fields Corner",
                    "labelPos": "N"
                },
                {
                    "coords": [
                        -71.118956,
                        42.373362
                    ],
                    "name": "Harvard",
                    "labelPos": "N"
                },
                {
                    "coords": [
                        -71.052391,
                        42.320685
                    ],
                    "name": "JFK/UMass",
                    "labelPos": "N"
                },
                {
                    "coords": [
                        -71.086176,
                        42.362491
                    ],
                    "name": "Kendall/MIT",
                    "labelPos": "N"
                },
                {
                    "coords": [
                        -71.029583,
                        42.275275
                    ],
                    "name": "North Quincy",
                    "labelPos": "N"
                },
                {
                    "coords": [
                        -71.062424,
                        42.356395
                    ],
                    "name": "Park Street",
                    "labelPos": "N"
                },
                {
                    "coords": [
                        -71.119149,
                        42.3884
                    ],
                    "name": "Porter",
                    "labelPos": "N"
                },
                {
                    "coords": [
                        -71.005409,
                        42.251809
                    ],
                    "name": "Quincy Center",
                    "labelPos": "N"
                },
                {
                    "coords": [
                        -71.055242,
                        42.352271
                    ],
                    "name": "South Station",
                    "labelPos": "N"
                },
                {
                    "coords": [
                        -71.020337,
                        42.266514
                    ],
                    "name": "Wollaston",
                    "labelPos": "N"
                },
                {
                    "coords": [
                        -71.053331,
                        42.31129
                    ],
                    "name": "Savin Hill",
                    "labelPos": "N"
                },
                {
                    "coords": [
                        -71.065738,
                        42.293126
                    ],
                    "name": "Shawmut",
                    "labelPos": "N"
                },
                {
                    "coords": [
                        -71.007153,
                        42.233391
                    ],
                    "name": "Quincy Adams",
                    "labelPos": "N"
                }
            ]
        },
        {
            "name": "Blue Line",
            "color": "#003DA5",
            "shiftCoords": [
                0,
                0
            ],
            "nodes": [
                {
                    "coords": [
                        -71.030395,
                        42.374262
                    ],
                    "name": "Airport",
                    "labelPos": "N"
                },
                {
                    "coords": [
                        -71.051652,
                        42.359784
                    ],
                    "name": "Aquarium",
                    "labelPos": "N"
                },
                {
                    "coords": [
                        -70.992319,
                        42.397542
                    ],
                    "name": "Beachmont",
                    "labelPos": "N"
                },
                {
                    "coords": [
                        -71.062037,
                        42.361365
                    ],
                    "name": "Bowdoin",
                    "labelPos": "N"
                },
                {
                    "coords": [
                        -71.059215,
                        42.359705
                    ],
                    "name": "Government Center",
                    "labelPos": "N"
                },
                {
                    "coords": [
                        -71.03953,
                        42.369119
                    ],
                    "name": "Maverick",
                    "labelPos": "N"
                },
                {
                    "coords": [
                        -71.004736,
                        42.386867
                    ],
                    "name": "Orient Heights",
                    "labelPos": "N"
                },
                {
                    "coords": [
                        -70.992533,
                        42.407843
                    ],
                    "name": "Revere Beach",
                    "labelPos": "N"
                },
                {
                    "coords": [
                        -70.997123,
                        42.390501
                    ],
                    "name": "Suffolk Downs",
                    "labelPos": "N"
                },
                {
                    "coords": [
                        -71.022865,
                        42.37964
                    ],
                    "name": "Wood Island",
                    "labelPos": "N"
                },
                {
                    "coords": [
                        -70.991648,
                        42.41342
                    ],
                    "name": "Wonderland",
                    "labelPos": "N"
                }
            ]
        }
    ]
}